kite_connection_manager/__init__.py
kite_connection_manager/connect_without_apikey.py
kite_connection_manager/connection_manager.py
kite_connection_manager/repeat_timer.py
kite_connection_manager/utils.py
tests/__init__.py
tests/login_tests.py
kite_connection_manager-0.4.9.dist-info/METADATA
kite_connection_manager-0.4.9.dist-info/WHEEL
kite_connection_manager-0.4.9.dist-info/top_level.txt
kite_connection_manager-0.4.9.dist-info/RECORD
