Metadata-Version: 2.1
Name: kite-connection-manager
Version: 0.4.9
Summary: Manage connections to KiteConnect
Home-page: https://github.com/shashwat7/KiteConnectionManager
Author: Shashwat Rastogi
Author-email: Shashwat Rastogi <shashwat1991@gmail.com>
Project-URL: Homepage, https://github.com/shashwat7/KiteConnectionManager
Classifier: Programming Language :: Python :: 3
Requires-Python: >=3.9
Requires-Dist: pyotp ~=2.6.0
Requires-Dist: kiteconnect ~=4.1.0
Requires-Dist: selenium ~=4.3.0
Requires-Dist: websockets
Requires-Dist: requests
Requires-Dist: beautifulsoup4
Requires-Dist: six
Requires-Dist: webdriver-manager
Requires-Dist: smart-open[gcs]
